odoo/addons/crm_lead_tag_multi_company/README.rst
odoo/addons/crm_lead_tag_multi_company/__init__.py
odoo/addons/crm_lead_tag_multi_company/__manifest__.py
odoo/addons/crm_lead_tag_multi_company/i18n/crm_lead_tag_multi_company.pot
odoo/addons/crm_lead_tag_multi_company/models/__init__.py
odoo/addons/crm_lead_tag_multi_company/models/crm_lead_tag.py
odoo/addons/crm_lead_tag_multi_company/readme/CONTRIBUTORS.rst
odoo/addons/crm_lead_tag_multi_company/readme/DESCRIPTION.rst
odoo/addons/crm_lead_tag_multi_company/security/crm_lead_tag.xml
odoo/addons/crm_lead_tag_multi_company/static/description/icon.png
odoo/addons/crm_lead_tag_multi_company/static/description/index.html
odoo/addons/crm_lead_tag_multi_company/views/crm_lead_tag.xml
odoo12_addon_crm_lead_tag_multi_company-12.0.1.0.0.99.dev4.dist-info/METADATA
odoo12_addon_crm_lead_tag_multi_company-12.0.1.0.0.99.dev4.dist-info/WHEEL
odoo12_addon_crm_lead_tag_multi_company-12.0.1.0.0.99.dev4.dist-info/top_level.txt
odoo12_addon_crm_lead_tag_multi_company-12.0.1.0.0.99.dev4.dist-info/RECORD
